{
  "owner": "paaksing",
  "repo": "django-cassiopeia",
  "description": "Django Integration of the League of Legends API framework Cassiopeia. Providing better tools for your Django/DRF based app and fixing issues related to co-ocurrency of cassiopeia and Django. Details in documentations",
  "language": "Python",
  "links": [{
    "name": "PyPi",
    "url": "https://pypi.org/project/django-cassiopeia/"
  }, {
    "name": "Documentation",
    "url": "https://paaksing.github.io/django-cassiopeia/"
  }],
  "metadata": {},
  "tags": [
    "v4",
    "rate-limiting",
    "production-caching"
  ]
}
